{
    "scene_id": 7,
    "phi": 0.2116,
    "num_objects": 4,
    "grid_size": [
        100,
        100
    ],
    "objects": [
        {
            "object_id": 0,
            "label": 11,
            "size": [
                23,
                23
            ],
            "initial_pos": [
                74,
                48
            ],
            "initial_relation": [
                0,
                0,
                0,
                0
            ],
            "target_pos": [
                46,
                54
            ],
            "target_relation": [
                0,
                0,
                0,
                0
            ]
        },
        {
            "object_id": 1,
            "label": 4,
            "size": [
                23,
                23
            ],
            "initial_pos": [
                83,
                86
            ],
            "initial_relation": [
                0,
                0,
                0,
                0
            ],
            "target_pos": [
                32,
                12
            ],
            "target_relation": [
                0,
                0,
                0,
                0
            ]
        },
        {
            "object_id": 2,
            "label": 5,
            "size": [
                23,
                23
            ],
            "initial_pos": [
                17,
                41
            ],
            "initial_relation": [
                0,
                0,
                0,
                0
            ],
            "target_pos": [
                74,
                12
            ],
            "target_relation": [
                0,
                0,
                0,
                0
            ]
        },
        {
            "object_id": 3,
            "label": 5,
            "size": [
                23,
                23
            ],
            "initial_pos": [
                22,
                74
            ],
            "initial_relation": [
                0,
                0,
                0,
                0
            ],
            "target_pos": [
                45,
                80
            ],
            "target_relation": [
                0,
                0,
                0,
                0
            ]
        }
    ]
}