{
    "scene_id": 9,
    "phi": 0.21233212430153905,
    "num_objects": 6,
    "grid_size": [
        101,
        101
    ],
    "objects": [
        {
            "object_id": 0,
            "label": 2,
            "size": [
                19,
                19
            ],
            "initial_pos": [
                50,
                89
            ],
            "initial_relation": [
                0,
                0,
                0,
                0,
                0,
                0
            ],
            "target_pos": [
                67,
                50
            ],
            "target_relation": [
                0,
                0,
                0,
                0,
                0,
                0
            ]
        },
        {
            "object_id": 1,
            "label": 6,
            "size": [
                19,
                19
            ],
            "initial_pos": [
                54,
                69
            ],
            "initial_relation": [
                0,
                0,
                0,
                0,
                0,
                0
            ],
            "target_pos": [
                14,
                77
            ],
            "target_relation": [
                0,
                0,
                0,
                0,
                0,
                0
            ]
        },
        {
            "object_id": 2,
            "label": 8,
            "size": [
                19,
                19
            ],
            "initial_pos": [
                90,
                84
            ],
            "initial_relation": [
                0,
                0,
                0,
                0,
                0,
                0
            ],
            "target_pos": [
                49,
                79
            ],
            "target_relation": [
                0,
                0,
                0,
                0,
                0,
                0
            ]
        },
        {
            "object_id": 3,
            "label": 10,
            "size": [
                19,
                19
            ],
            "initial_pos": [
                12,
                87
            ],
            "initial_relation": [
                0,
                0,
                0,
                0,
                0,
                0
            ],
            "target_pos": [
                48,
                26
            ],
            "target_relation": [
                0,
                0,
                0,
                0,
                0,
                0
            ]
        },
        {
            "object_id": 4,
            "label": 6,
            "size": [
                19,
                19
            ],
            "initial_pos": [
                56,
                42
            ],
            "initial_relation": [
                0,
                0,
                0,
                0,
                0,
                0
            ],
            "target_pos": [
                9,
                36
            ],
            "target_relation": [
                0,
                0,
                0,
                0,
                0,
                0
            ]
        },
        {
            "object_id": 5,
            "label": 9,
            "size": [
                19,
                19
            ],
            "initial_pos": [
                15,
                68
            ],
            "initial_relation": [
                0,
                0,
                0,
                0,
                0,
                0
            ],
            "target_pos": [
                90,
                40
            ],
            "target_relation": [
                0,
                0,
                0,
                0,
                0,
                0
            ]
        }
    ]
}