{
    "scene_id": 28,
    "phi": 0.5,
    "num_objects": 8,
    "grid_size": [
        100,
        100
    ],
    "objects": [
        {
            "object_id": 0,
            "label": 11,
            "size": [
                25,
                25
            ],
            "initial_pos": [
                84,
                29
            ],
            "initial_relation": [
                0,
                0,
                0,
                0,
                0,
                0,
                0,
                0
            ],
            "target_pos": [
                17,
                21
            ],
            "target_relation": [
                0,
                0,
                0,
                0,
                0,
                0,
                0,
                0
            ]
        },
        {
            "object_id": 1,
            "label": 0,
            "size": [
                25,
                25
            ],
            "initial_pos": [
                51,
                49
            ],
            "initial_relation": [
                0,
                0,
                0,
                0,
                0,
                0,
                0,
                0
            ],
            "target_pos": [
                61,
                47
            ],
            "target_relation": [
                0,
                0,
                0,
                0,
                0,
                0,
                0,
                0
            ]
        },
        {
            "object_id": 2,
            "label": 4,
            "size": [
                25,
                25
            ],
            "initial_pos": [
                76,
                57
            ],
            "initial_relation": [
                0,
                0,
                0,
                0,
                0,
                0,
                0,
                0
            ],
            "target_pos": [
                40,
                86
            ],
            "target_relation": [
                0,
                0,
                0,
                0,
                0,
                0,
                0,
                0
            ]
        },
        {
            "object_id": 3,
            "label": 3,
            "size": [
                25,
                25
            ],
            "initial_pos": [
                23,
                55
            ],
            "initial_relation": [
                0,
                0,
                0,
                0,
                0,
                0,
                0,
                0
            ],
            "target_pos": [
                82,
                80
            ],
            "target_relation": [
                0,
                0,
                0,
                0,
                0,
                0,
                0,
                0
            ]
        },
        {
            "object_id": 4,
            "label": 4,
            "size": [
                25,
                25
            ],
            "initial_pos": [
                46,
                15
            ],
            "initial_relation": [
                0,
                0,
                0,
                0,
                0,
                0,
                0,
                0
            ],
            "target_pos": [
                23,
                50
            ],
            "target_relation": [
                0,
                0,
                0,
                0,
                0,
                0,
                0,
                0
            ]
        },
        {
            "object_id": 5,
            "label": 0,
            "size": [
                25,
                25
            ],
            "initial_pos": [
                13,
                29
            ],
            "initial_relation": [
                0,
                0,
                0,
                0,
                0,
                0,
                0,
                0
            ],
            "target_pos": [
                79,
                13
            ],
            "target_relation": [
                0,
                0,
                0,
                0,
                0,
                0,
                0,
                0
            ]
        },
        {
            "object_id": 6,
            "label": 6,
            "size": [
                25,
                25
            ],
            "initial_pos": [
                37,
                86
            ],
            "initial_relation": [
                0,
                0,
                0,
                0,
                0,
                0,
                0,
                0
            ],
            "target_pos": [
                12,
                80
            ],
            "target_relation": [
                0,
                0,
                0,
                0,
                0,
                0,
                0,
                0
            ]
        },
        {
            "object_id": 7,
            "label": 4,
            "size": [
                25,
                25
            ],
            "initial_pos": [
                76,
                83
            ],
            "initial_relation": [
                0,
                0,
                0,
                0,
                0,
                0,
                0,
                0
            ],
            "target_pos": [
                47,
                12
            ],
            "target_relation": [
                0,
                0,
                0,
                0,
                0,
                0,
                0,
                0
            ]
        }
    ]
}