{
    "scene_id": 28,
    "phi": 0.5043,
    "num_objects": 3,
    "grid_size": [
        100,
        100
    ],
    "objects": [
        {
            "object_id": 0,
            "label": 3,
            "size": [
                41,
                41
            ],
            "initial_pos": [
                22,
                74
            ],
            "initial_relation": [
                0,
                0,
                0
            ],
            "target_pos": [
                20,
                54
            ],
            "target_relation": [
                0,
                0,
                0
            ]
        },
        {
            "object_id": 1,
            "label": 3,
            "size": [
                41,
                41
            ],
            "initial_pos": [
                75,
                42
            ],
            "initial_relation": [
                0,
                0,
                0
            ],
            "target_pos": [
                70,
                75
            ],
            "target_relation": [
                0,
                0,
                0
            ]
        },
        {
            "object_id": 2,
            "label": 11,
            "size": [
                41,
                41
            ],
            "initial_pos": [
                21,
                21
            ],
            "initial_relation": [
                0,
                0,
                0
            ],
            "target_pos": [
                77,
                25
            ],
            "target_relation": [
                0,
                0,
                0
            ]
        }
    ]
}