{
    "scene_id": 3,
    "phi": 0.1875,
    "num_objects": 6,
    "grid_size": [
        100,
        200
    ],
    "objects": [
        {
            "object_id": 0,
            "label": 6,
            "size": [
                25,
                25
            ],
            "initial_pos": [
                87,
                178
            ],
            "target_pos": [
                80,
                39
            ],
            "initial_base_id": null,
            "target_base_id": null
        },
        {
            "object_id": 1,
            "label": 11,
            "size": [
                25,
                25
            ],
            "initial_pos": [
                17,
                49
            ],
            "target_pos": [
                12,
                150
            ],
            "initial_base_id": null,
            "target_base_id": null
        },
        {
            "object_id": 2,
            "label": 3,
            "size": [
                25,
                25
            ],
            "initial_pos": [
                24,
                20
            ],
            "target_pos": [
                43,
                17
            ],
            "initial_base_id": null,
            "target_base_id": null
        },
        {
            "object_id": 3,
            "label": 0,
            "size": [
                25,
                25
            ],
            "initial_pos": [
                40,
                185
            ],
            "target_pos": [
                64,
                156
            ],
            "initial_base_id": null,
            "target_base_id": null
        },
        {
            "object_id": 4,
            "label": 4,
            "size": [
                25,
                25
            ],
            "initial_pos": [
                60,
                52
            ],
            "target_pos": [
                42,
                182
            ],
            "initial_base_id": null,
            "target_base_id": null
        },
        {
            "object_id": 5,
            "label": 3,
            "size": [
                25,
                25
            ],
            "initial_pos": [
                56,
                25
            ],
            "target_pos": [
                87,
                184
            ],
            "initial_base_id": null,
            "target_base_id": null
        }
    ]
}