{
    "scene_id": 11,
    "phi": 0.20713265356386384,
    "num_objects": 5,
    "grid_size": [
        101,
        201
    ],
    "objects": [
        {
            "object_id": 0,
            "label": 3,
            "size": [
                29,
                29
            ],
            "initial_pos": [
                20,
                161
            ],
            "initial_relation": [
                0,
                0,
                0,
                0,
                0
            ],
            "target_pos": [
                69,
                143
            ],
            "target_relation": [
                0,
                0,
                0,
                0,
                0
            ]
        },
        {
            "object_id": 1,
            "label": 1,
            "size": [
                29,
                29
            ],
            "initial_pos": [
                15,
                16
            ],
            "initial_relation": [
                0,
                0,
                0,
                0,
                0
            ],
            "target_pos": [
                55,
                20
            ],
            "target_relation": [
                0,
                0,
                0,
                0,
                0
            ]
        },
        {
            "object_id": 2,
            "label": 4,
            "size": [
                29,
                29
            ],
            "initial_pos": [
                61,
                128
            ],
            "initial_relation": [
                0,
                0,
                0,
                0,
                0
            ],
            "target_pos": [
                22,
                45
            ],
            "target_relation": [
                0,
                0,
                0,
                0,
                0
            ]
        },
        {
            "object_id": 3,
            "label": 1,
            "size": [
                29,
                29
            ],
            "initial_pos": [
                55,
                164
            ],
            "initial_relation": [
                0,
                0,
                0,
                0,
                0
            ],
            "target_pos": [
                34,
                146
            ],
            "target_relation": [
                0,
                0,
                0,
                0,
                0
            ]
        },
        {
            "object_id": 4,
            "label": 5,
            "size": [
                29,
                29
            ],
            "initial_pos": [
                86,
                95
            ],
            "initial_relation": [
                0,
                0,
                0,
                0,
                0
            ],
            "target_pos": [
                27,
                105
            ],
            "target_relation": [
                0,
                0,
                0,
                0,
                0
            ]
        }
    ]
}