{
    "scene_id": 24,
    "phi": 0.1922,
    "num_objects": 4,
    "grid_size": [
        100,
        200
    ],
    "objects": [
        {
            "object_id": 0,
            "label": 1,
            "size": [
                31,
                31
            ],
            "initial_pos": [
                62,
                172
            ],
            "target_pos": [
                55,
                156
            ],
            "initial_base_id": null,
            "target_base_id": null
        },
        {
            "object_id": 1,
            "label": 6,
            "size": [
                31,
                31
            ],
            "initial_pos": [
                39,
                26
            ],
            "target_pos": [
                41,
                26
            ],
            "initial_base_id": null,
            "target_base_id": null
        },
        {
            "object_id": 2,
            "label": 2,
            "size": [
                31,
                31
            ],
            "initial_pos": [
                77,
                23
            ],
            "target_pos": [
                76,
                22
            ],
            "initial_base_id": null,
            "target_base_id": null
        },
        {
            "object_id": 3,
            "label": 11,
            "size": [
                31,
                31
            ],
            "initial_pos": [
                28,
                166
            ],
            "target_pos": [
                19,
                147
            ],
            "initial_base_id": null,
            "target_base_id": null
        }
    ]
}