{
    "scene_id": 38,
    "phi": 0.18471996453376682,
    "num_objects": 6,
    "grid_size": [
        101,
        201
    ],
    "objects": [
        {
            "object_id": 0,
            "label": 1,
            "size": [
                25,
                25
            ],
            "initial_pos": [
                66,
                45
            ],
            "initial_relation": [
                0,
                0,
                0,
                0,
                0,
                0
            ],
            "target_pos": [
                58,
                36
            ],
            "target_relation": [
                0,
                0,
                0,
                0,
                0,
                0
            ]
        },
        {
            "object_id": 1,
            "label": 8,
            "size": [
                25,
                25
            ],
            "initial_pos": [
                40,
                154
            ],
            "initial_relation": [
                0,
                0,
                0,
                0,
                0,
                0
            ],
            "target_pos": [
                31,
                15
            ],
            "target_relation": [
                0,
                0,
                0,
                0,
                0,
                0
            ]
        },
        {
            "object_id": 2,
            "label": 5,
            "size": [
                25,
                25
            ],
            "initial_pos": [
                45,
                92
            ],
            "initial_relation": [
                0,
                0,
                0,
                0,
                0,
                0
            ],
            "target_pos": [
                40,
                96
            ],
            "target_relation": [
                0,
                0,
                0,
                0,
                0,
                0
            ]
        },
        {
            "object_id": 3,
            "label": 8,
            "size": [
                25,
                25
            ],
            "initial_pos": [
                39,
                59
            ],
            "initial_relation": [
                0,
                0,
                0,
                0,
                0,
                0
            ],
            "target_pos": [
                78,
                142
            ],
            "target_relation": [
                0,
                0,
                0,
                0,
                0,
                0
            ]
        },
        {
            "object_id": 4,
            "label": 2,
            "size": [
                25,
                25
            ],
            "initial_pos": [
                14,
                73
            ],
            "initial_relation": [
                0,
                0,
                0,
                0,
                0,
                0
            ],
            "target_pos": [
                60,
                68
            ],
            "target_relation": [
                0,
                0,
                0,
                0,
                0,
                0
            ]
        },
        {
            "object_id": 5,
            "label": 8,
            "size": [
                25,
                25
            ],
            "initial_pos": [
                86,
                186
            ],
            "initial_relation": [
                0,
                0,
                0,
                0,
                0,
                0
            ],
            "target_pos": [
                17,
                45
            ],
            "target_relation": [
                0,
                0,
                0,
                0,
                0,
                0
            ]
        }
    ]
}