{
    "scene_id": 1,
    "phi": 0.18471996453376682,
    "num_objects": 6,
    "grid_size": [
        101,
        201
    ],
    "objects": [
        {
            "object_id": 0,
            "label": 7,
            "size": [
                25,
                25
            ],
            "initial_pos": [
                42,
                137
            ],
            "initial_relation": [
                0,
                0,
                0,
                0,
                0,
                0
            ],
            "target_pos": [
                67,
                162
            ],
            "target_relation": [
                0,
                0,
                0,
                0,
                0,
                0
            ]
        },
        {
            "object_id": 1,
            "label": 11,
            "size": [
                25,
                25
            ],
            "initial_pos": [
                40,
                188
            ],
            "initial_relation": [
                0,
                0,
                0,
                0,
                0,
                0
            ],
            "target_pos": [
                33,
                112
            ],
            "target_relation": [
                0,
                0,
                0,
                0,
                0,
                0
            ]
        },
        {
            "object_id": 2,
            "label": 3,
            "size": [
                25,
                25
            ],
            "initial_pos": [
                13,
                75
            ],
            "initial_relation": [
                0,
                0,
                0,
                0,
                0,
                0
            ],
            "target_pos": [
                12,
                160
            ],
            "target_relation": [
                0,
                0,
                0,
                0,
                0,
                0
            ]
        },
        {
            "object_id": 3,
            "label": 7,
            "size": [
                25,
                25
            ],
            "initial_pos": [
                71,
                173
            ],
            "initial_relation": [
                0,
                0,
                0,
                0,
                0,
                0
            ],
            "target_pos": [
                26,
                13
            ],
            "target_relation": [
                0,
                0,
                0,
                0,
                0,
                0
            ]
        },
        {
            "object_id": 4,
            "label": 11,
            "size": [
                25,
                25
            ],
            "initial_pos": [
                75,
                33
            ],
            "initial_relation": [
                0,
                0,
                0,
                0,
                0,
                0
            ],
            "target_pos": [
                49,
                82
            ],
            "target_relation": [
                0,
                0,
                0,
                0,
                0,
                0
            ]
        },
        {
            "object_id": 5,
            "label": 9,
            "size": [
                25,
                25
            ],
            "initial_pos": [
                86,
                147
            ],
            "initial_relation": [
                0,
                0,
                0,
                0,
                0,
                0
            ],
            "target_pos": [
                39,
                152
            ],
            "target_relation": [
                0,
                0,
                0,
                0,
                0,
                0
            ]
        }
    ]
}