{
    "scene_id": 32,
    "phi": 0.2023,
    "num_objects": 7,
    "grid_size": [
        100,
        100
    ],
    "objects": [
        {
            "object_id": 0,
            "label": 9,
            "size": [
                17,
                17
            ],
            "initial_pos": [
                85,
                78
            ],
            "initial_relation": [
                0,
                0,
                0,
                0,
                0,
                0,
                0
            ],
            "target_pos": [
                25,
                83
            ],
            "target_relation": [
                0,
                0,
                0,
                0,
                0,
                0,
                0
            ]
        },
        {
            "object_id": 1,
            "label": 8,
            "size": [
                17,
                17
            ],
            "initial_pos": [
                57,
                72
            ],
            "initial_relation": [
                0,
                0,
                0,
                0,
                0,
                0,
                0
            ],
            "target_pos": [
                74,
                36
            ],
            "target_relation": [
                0,
                0,
                0,
                0,
                0,
                0,
                0
            ]
        },
        {
            "object_id": 2,
            "label": 7,
            "size": [
                17,
                17
            ],
            "initial_pos": [
                91,
                17
            ],
            "initial_relation": [
                0,
                0,
                0,
                0,
                0,
                0,
                0
            ],
            "target_pos": [
                9,
                54
            ],
            "target_relation": [
                0,
                0,
                0,
                0,
                0,
                0,
                0
            ]
        },
        {
            "object_id": 3,
            "label": 6,
            "size": [
                17,
                17
            ],
            "initial_pos": [
                75,
                54
            ],
            "initial_relation": [
                0,
                0,
                0,
                0,
                0,
                0,
                0
            ],
            "target_pos": [
                65,
                66
            ],
            "target_relation": [
                0,
                0,
                0,
                0,
                0,
                0,
                0
            ]
        },
        {
            "object_id": 4,
            "label": 9,
            "size": [
                17,
                17
            ],
            "initial_pos": [
                36,
                82
            ],
            "initial_relation": [
                0,
                0,
                0,
                0,
                0,
                0,
                0
            ],
            "target_pos": [
                41,
                36
            ],
            "target_relation": [
                0,
                0,
                0,
                0,
                0,
                0,
                0
            ]
        },
        {
            "object_id": 5,
            "label": 2,
            "size": [
                17,
                17
            ],
            "initial_pos": [
                30,
                23
            ],
            "initial_relation": [
                0,
                0,
                0,
                0,
                0,
                0,
                0
            ],
            "target_pos": [
                45,
                91
            ],
            "target_relation": [
                0,
                0,
                0,
                0,
                0,
                0,
                0
            ]
        },
        {
            "object_id": 6,
            "label": 0,
            "size": [
                17,
                17
            ],
            "initial_pos": [
                63,
                26
            ],
            "initial_relation": [
                0,
                0,
                0,
                0,
                0,
                0,
                0
            ],
            "target_pos": [
                48,
                16
            ],
            "target_relation": [
                0,
                0,
                0,
                0,
                0,
                0,
                0
            ]
        }
    ]
}