{
    "scene_id": 29,
    "phi": 0.2023,
    "num_objects": 7,
    "grid_size": [
        100,
        100
    ],
    "objects": [
        {
            "object_id": 0,
            "label": 2,
            "size": [
                17,
                17
            ],
            "initial_pos": [
                84,
                44
            ],
            "target_pos": [
                45,
                49
            ],
            "initial_base_id": null,
            "target_base_id": null
        },
        {
            "object_id": 1,
            "label": 8,
            "size": [
                17,
                17
            ],
            "initial_pos": [
                59,
                23
            ],
            "target_pos": [
                68,
                50
            ],
            "initial_base_id": null,
            "target_base_id": null
        },
        {
            "object_id": 2,
            "label": 0,
            "size": [
                17,
                17
            ],
            "initial_pos": [
                76,
                12
            ],
            "target_pos": [
                56,
                77
            ],
            "initial_base_id": null,
            "target_base_id": null
        },
        {
            "object_id": 3,
            "label": 2,
            "size": [
                17,
                17
            ],
            "initial_pos": [
                41,
                73
            ],
            "target_pos": [
                15,
                37
            ],
            "initial_base_id": null,
            "target_base_id": null
        },
        {
            "object_id": 4,
            "label": 6,
            "size": [
                17,
                17
            ],
            "initial_pos": [
                11,
                41
            ],
            "target_pos": [
                88,
                9
            ],
            "initial_base_id": null,
            "target_base_id": null
        },
        {
            "object_id": 5,
            "label": 1,
            "size": [
                17,
                17
            ],
            "initial_pos": [
                83,
                69
            ],
            "target_pos": [
                68,
                28
            ],
            "initial_base_id": null,
            "target_base_id": null
        },
        {
            "object_id": 6,
            "label": 5,
            "size": [
                17,
                17
            ],
            "initial_pos": [
                60,
                57
            ],
            "target_pos": [
                19,
                66
            ],
            "initial_base_id": null,
            "target_base_id": null
        }
    ]
}